<annotation>
	<folder>all_images</folder>
	<filename>defected4_aug_3.jpg</filename>
	<path>C:\Users\Kavya M\Downloads\Data_Augmentation_Tool\Data_augmentation\all_images\defected4_aug_3.jpg</path>
	<source>
		<database>Unknown</database>
	</source>
	<size>
		<width>224</width>
		<height>224</height>
		<depth>1</depth>
	</size>
	<segmented>0</segmented>
	<object>
		<name>tiny_holes</name>
		<pose>Unspecified</pose>
		<truncated>0</truncated>
		<difficult>0</difficult>
		<bndbox>
			<xmin>29</xmin>
			<ymin>152</ymin>
			<xmax>41</xmax>
			<ymax>166</ymax>
		</bndbox>
	</object>
	<object>
		<name>tiny_holes</name>
		<pose>Unspecified</pose>
		<truncated>0</truncated>
		<difficult>0</difficult>
		<bndbox>
			<xmin>8</xmin>
			<ymin>197</ymin>
			<xmax>22</xmax>
			<ymax>210</ymax>
		</bndbox>
	</object>
	<object>
		<name>tiny_holes</name>
		<pose>Unspecified</pose>
		<truncated>0</truncated>
		<difficult>0</difficult>
		<bndbox>
			<xmin>204</xmin>
			<ymin>202</ymin>
			<xmax>220</xmax>
			<ymax>219</ymax>
		</bndbox>
	</object>
</annotation>
